.hgtags
CHANGES.txt
LICENSE.txt
README.txt
setup.py
js/__init__.py
js.tableselect.egg-info/PKG-INFO
js.tableselect.egg-info/SOURCES.txt
js.tableselect.egg-info/dependency_links.txt
js.tableselect.egg-info/entry_points.txt
js.tableselect.egg-info/namespace_packages.txt
js.tableselect.egg-info/not-zip-safe
js.tableselect.egg-info/requires.txt
js.tableselect.egg-info/top_level.txt
js/tableselect/__init__.py
js/tableselect/resources/tableselect.css
js/tableselect/resources/tableselect.js