Metadata-Version: 1.0
Name: js.tableselect
Version: 0.3
Summary: Fanstatic package providing a js table select widget.
Home-page: UNKNOWN
Author: Daniel Havlik
Author-email: dh@gocept.com
License: BSD
Platform: UNKNOWN
